fern_nav_builder/__init__.py
fern_nav_builder/nav.py
fern_nav_builder-0.1.0.dist-info/METADATA
fern_nav_builder-0.1.0.dist-info/WHEEL
fern_nav_builder-0.1.0.dist-info/entry_points.txt
fern_nav_builder-0.1.0.dist-info/RECORD
